{
  "adr_en": "Bar Pacific, G/F, 671 GILLIES AVE.,NORTH, HUNG HOM, KOWLOON CITY, KOWLOON",
  "adr_tc": "\u4e5d\u9f8d\u7d05\u78e1\u6a5f\u5229\u58eb\u8def\u5317671\u865f\u5730\u4e0b \u592a\u5e73\u6d0b\u9152\u5427",
  "geocode_en": [
    {
      "address_components": [
        {
          "long_name": "G/F",
          "short_name": "G/F",
          "types": [
            "subpremise"
          ]
        },
        {
          "long_name": "663",
          "short_name": "663",
          "types": [
            "street_number"
          ]
        },
        {
          "long_name": "Gillies Avenue North",
          "short_name": "Gillies Ave N",
          "types": [
            "route"
          ]
        },
        {
          "long_name": "Lo Lung Hang",
          "short_name": "Lo Lung Hang",
          "types": [
            "neighborhood",
            "political"
          ]
        },
        {
          "long_name": "Kowloon",
          "short_name": "Kowloon",
          "types": [
            "administrative_area_level_1",
            "political"
          ]
        },
        {
          "long_name": "Hong Kong",
          "short_name": "HK",
          "types": [
            "country",
            "political"
          ]
        }
      ],
      "formatted_address": "G/F, 663 Gillies Ave N, Lo Lung Hang, Hong Kong",
      "geometry": {
        "location": {
          "lat": 22.3124007,
          "lng": 114.1873938
        },
        "location_type": "ROOFTOP",
        "viewport": {
          "northeast": {
            "lat": 22.3137496802915,
            "lng": 114.1887427802915
          },
          "southwest": {
            "lat": 22.3110517197085,
            "lng": 114.1860448197085
          }
        }
      },
      "place_id": "ChIJb5cfMdkABDQR-REkKCINuQ0",
      "plus_code": {
        "compound_code": "856P+XX Hong Kong",
        "global_code": "7PJP856P+XX"
      },
      "types": [
        "bar",
        "establishment",
        "point_of_interest"
      ]
    }
  ],
  "geocode_tc": [
    {
      "address_components": [
        {
          "long_name": "G/F",
          "short_name": "G/F",
          "types": [
            "subpremise"
          ]
        },
        {
          "long_name": "663",
          "short_name": "663",
          "types": [
            "street_number"
          ]
        },
        {
          "long_name": "Gillies Avenue North",
          "short_name": "Gillies Ave N",
          "types": [
            "route"
          ]
        },
        {
          "long_name": "Lo Lung Hang",
          "short_name": "Lo Lung Hang",
          "types": [
            "neighborhood",
            "political"
          ]
        },
        {
          "long_name": "Kowloon",
          "short_name": "Kowloon",
          "types": [
            "administrative_area_level_1",
            "political"
          ]
        },
        {
          "long_name": "\u9999\u6e2f",
          "short_name": "HK",
          "types": [
            "country",
            "political"
          ]
        }
      ],
      "formatted_address": "G/F, 663 Gillies Ave N, Lo Lung Hang, \u9999\u6e2f",
      "geometry": {
        "location": {
          "lat": 22.3124007,
          "lng": 114.1873938
        },
        "location_type": "ROOFTOP",
        "viewport": {
          "northeast": {
            "lat": 22.3137496802915,
            "lng": 114.1887427802915
          },
          "southwest": {
            "lat": 22.3110517197085,
            "lng": 114.1860448197085
          }
        }
      },
      "place_id": "ChIJb5cfMdkABDQR-REkKCINuQ0",
      "plus_code": {
        "compound_code": "856P+XX \u9999\u6e2f",
        "global_code": "7PJP856P+XX"
      },
      "types": [
        "bar",
        "establishment",
        "point_of_interest"
      ]
    }
  ],
  "licno": "3152234790",
  "timestamp": 1564975666,
  "version": "1564966095"
}
